resoup/__init__.py
resoup/api_with_tools.py
resoup/api_with_tools.pyi
resoup/avoid_sslerror.py
resoup/broadcast_list.py
resoup/broadcast_list.pyi
resoup/contants.py
resoup/custom_defaults.py
resoup/custom_defaults.pyi
resoup/dealing_unhashable_args.py
resoup/exceptions.py
resoup/full_dunder.py
resoup/header_utils.py
resoup/requests_.py
resoup/response_proxy.py
resoup/sessions_with_tools.py
resoup/sessions_with_tools.pyi
resoup/souptools.py
resoup-0.5.2.dist-info/entry_points.txt
resoup-0.5.2.dist-info/LICENSE
resoup-0.5.2.dist-info/METADATA
resoup-0.5.2.dist-info/WHEEL
resoup-0.5.2.dist-info/RECORD
