Metadata-Version: 2.1
Name: resoup
Version: 0.5.2
Summary: Various convenient features related to requests.
License: MIT
Keywords: requests,bs4,BeautifulSoup,async,caching,cache
Author: ilotoki0804
Author-email: ilotoki0804@gmail.com
Requires-Python: >=3.10,<4.0
Classifier: Environment :: Web Environment
Classifier: Framework :: AsyncIO
Classifier: Intended Audience :: Developers
Classifier: License :: OSI Approved :: MIT License
Classifier: Operating System :: OS Independent
Classifier: Programming Language :: Python :: 3
Classifier: Programming Language :: Python :: 3.10
Classifier: Programming Language :: Python :: 3.11
Classifier: Programming Language :: Python :: 3.12
Classifier: Topic :: Internet :: WWW/HTTP
Requires-Dist: beautifulsoup4 (>=4.12.2,<5.0.0)
Requires-Dist: frozendict (>=2.3.10,<3.0.0)
Requires-Dist: requests (>=2.31.0,<3.0.0)
Requires-Dist: typing-extensions (>=4.8.0,<5.0.0)
Project-URL: Changelog, https://github.com/ilotoki0804/resoup#relese-note
Project-URL: Documentation, https://github.com/ilotoki0804/resoup
Project-URL: Issues, https://github.com/ilotoki0804/resoup/issues
Project-URL: Repository, https://github.com/ilotoki0804/resoup
